[{"code":"AF","name":"Afghanistan","flag":""},{"code":"DE","name":"Alamagn","flag":""},{"code":"AL","name":"Albania","flag":""},{"code":"DZ","name":"Aljeria","flag":""},{"code":"AD","name":"Andorra","flag":""},{"code":"AO","name":"Angola","flag":""},{"code":"AI","name":"Anguilla","flag":""},{"code":"AQ","name":"Antarktika","flag":""},{"code":"AG","name":"Antigua ha Barbuda","flag":""},{"code":"CI","name":"Aod an Olifant","flag":""},{"code":"AU","name":"Aostralia","flag":""},{"code":"AT","name":"Aostria","flag":""},{"code":"RE","name":"Ar Re眉nion","flag":"佛"},{"code":"SA","name":"Arabia Saoudat","flag":"葛"},{"code":"AR","name":"Arc始hantina","flag":""},{"code":"AM","name":"Armenia","flag":""},{"code":"AW","name":"Aruba","flag":""},{"code":"AZ","name":"Azerbaidjan","flag":""},{"code":"BS","name":"Bahamas","flag":"ю"},{"code":"BH","name":"Bahrein","flag":"ю"},{"code":"BD","name":"Bangladesh","flag":"ю"},{"code":"BB","name":"Barbados","flag":"ю"},{"code":"BY","name":"Belarus","flag":"ю"},{"code":"BE","name":"Belgia","flag":"ю"},{"code":"BZ","name":"Belize","flag":"ю"},{"code":"BJ","name":"Benin","flag":"ю"},{"code":"BM","name":"Bermuda","flag":"ю"},{"code":"BT","name":"Bhoutan","flag":"ю"},{"code":"BO","name":"Bolivia","flag":"ю"},{"code":"BA","name":"Bosnia ha Herzegovina","flag":"ю"},{"code":"BW","name":"Botswana","flag":"ю"},{"code":"BR","name":"Brazil","flag":"ю"},{"code":"BN","name":"Brunei","flag":"ю"},{"code":"BG","name":"Bulgaria","flag":"ю"},{"code":"BF","name":"Burkina Faso","flag":"ю"},{"code":"BI","name":"Burundi","flag":"ю"},{"code":"EA","name":"Ceuta ha Melilla"},{"code":"CL","name":"Chile","flag":""},{"code":"CR","name":"Costa Rica","flag":""},{"code":"CW","name":"Cura莽ao"},{"code":"DK","name":"Danmark","flag":""},{"code":"DG","name":"Diego Garcia"},{"code":"DJ","name":"Djibouti","flag":""},{"code":"DM","name":"Dominica","flag":""},{"code":"TF","name":"Douaro霉 aostral Fra帽s"},{"code":"EC","name":"Ecuador","flag":""},{"code":"EG","name":"Egipt","flag":""},{"code":"AE","name":"Emirelezhio霉 Arab Unanet","flag":""},{"code":"AC","name":"Enez Ascension"},{"code":"CX","name":"Enez Christmas","flag":""},{"code":"NF","name":"Enez Norfolk","flag":"仇"},{"code":"PN","name":"Enez Pitcairn","flag":"叼"},{"code":"IM","name":"Enez Vanav","flag":""},{"code":"ER","name":"Eritrea","flag":""},{"code":"EE","name":"Estonia","flag":""},{"code":"ET","name":"Etiopia","flag":""},{"code":"EZ","name":"Eurozone"},{"code":"FJ","name":"Fidji","flag":""},{"code":"PH","name":"Filipinez","flag":"叼"},{"code":"FI","name":"Finland","flag":""},{"code":"FR","name":"Fra帽s","flag":""},{"code":"GA","name":"Gabon","flag":""},{"code":"GM","name":"Gambia","flag":""},{"code":"GH","name":"Ghana","flag":""},{"code":"GN","name":"Ginea","flag":""},{"code":"GQ","name":"Ginea ar C始heheder","flag":""},{"code":"GW","name":"Ginea-Bissau","flag":""},{"code":"GD","name":"Grenada","flag":""},{"code":"GR","name":"Gres","flag":""},{"code":"GL","name":"Greunland","flag":""},{"code":"GU","name":"Guam","flag":""},{"code":"GT","name":"Guatemala","flag":""},{"code":"GY","name":"Guyana","flag":""},{"code":"GP","name":"Gwadeloup","flag":""},{"code":"GG","name":"Gwernenez","flag":""},{"code":"GF","name":"Gwiana c始hall","flag":""},{"code":"HT","name":"Haiti","flag":""},{"code":"HN","name":"Honduras","flag":""},{"code":"HK","name":"Hong Kong RMD Sina","flag":""},{"code":"HU","name":"Hungaria","flag":""},{"code":"IN","name":"India","flag":""},{"code":"ID","name":"Indonezia","flag":""},{"code":"AX","name":"Inizi land","flag":""},{"code":"KY","name":"Inizi Cayman","flag":"梆"},{"code":"CK","name":"Inizi Cook","flag":""},{"code":"UM","name":"Inizi diabell ar Stado霉-Unanet"},{"code":"FO","name":"Inizi Faero","flag":""},{"code":"FK","name":"Inizi Falkland","flag":""},{"code":"GS","name":"Inizi Georgia ar Su hag Inizi Sandwich ar Su","flag":""},{"code":"VI","name":"Inizi Gwerc始h ar Stado霉-Unanet","flag":"火"},{"code":"VG","name":"Inizi Gwerc始h Breizh-Veur","flag":"火"},{"code":"IC","name":"Inizi Kanariez"},{"code":"CC","name":"Inizi Kokoz","flag":""},{"code":"MP","name":"Inizi Mariana an Norzh","flag":"拆"},{"code":"MH","name":"Inizi Marshall","flag":"拆"},{"code":"SB","name":"Inizi Salomon","flag":"葛"},{"code":"TC","name":"Inizi Turks ha Caicos","flag":"桂"},{"code":"IR","name":"Iran","flag":""},{"code":"IQ","name":"Iraq","flag":""},{"code":"IS","name":"Island","flag":""},{"code":"IL","name":"Israel","flag":""},{"code":"IT","name":"Italia","flag":""},{"code":"IE","name":"Iwerzhon","flag":""},{"code":"NL","name":"Izelvroio霉","flag":"仇"},{"code":"JM","name":"Jamaika","flag":""},{"code":"JP","name":"Japan","flag":""},{"code":"JE","name":"Jerzenez","flag":""},{"code":"GI","name":"Jibraltar","flag":""},{"code":"JO","name":"Jordania","flag":""},{"code":"GE","name":"Jorjia","flag":""},{"code":"CV","name":"Kab-Glas","flag":""},{"code":"NC","name":"Kaledonia Nevez","flag":"仇"},{"code":"KH","name":"Kambodja","flag":"梆"},{"code":"CM","name":"Kameroun","flag":""},{"code":"CA","name":"Kanada","flag":""},{"code":"BQ","name":"Karib Nederlandat"},{"code":"KZ","name":"Kazakstan","flag":"梆"},{"code":"KE","name":"Kenya","flag":"梆"},{"code":"CY","name":"Kiprenez","flag":""},{"code":"KI","name":"Kiribati","flag":"梆"},{"code":"CO","name":"Kolombia","flag":""},{"code":"KM","name":"Komorez","flag":"梆"},{"code":"CG","name":"Kongo - Brazzaville","flag":""},{"code":"CD","name":"Kongo - Kinshasa","flag":""},{"code":"KP","name":"Korea an Norzh","flag":"梆"},{"code":"KR","name":"Korea ar Su","flag":"梆"},{"code":"XK","name":"Kosovo"},{"code":"KW","name":"Koweit","flag":"梆"},{"code":"HR","name":"Kroatia","flag":""},{"code":"CU","name":"Kuba","flag":""},{"code":"KG","name":"Kyrgyzstan","flag":"梆"},{"code":"LA","name":"Laos","flag":"别"},{"code":"LV","name":"Latvia","flag":"别"},{"code":"LS","name":"Lesotho","flag":"别"},{"code":"LB","name":"Liban","flag":"别"},{"code":"LR","name":"Liberia","flag":"别"},{"code":"LY","name":"Libia","flag":"别"},{"code":"LI","name":"Liechtenstein","flag":"别"},{"code":"LT","name":"Lituania","flag":"别"},{"code":"LU","name":"Luksembourg","flag":"别"},{"code":"MO","name":"Macau RMD Sina","flag":"拆"},{"code":"MG","name":"Madagaskar","flag":"拆"},{"code":"MK","name":"Makedonia","flag":"拆"},{"code":"MW","name":"Malawi","flag":"拆"},{"code":"MY","name":"Malaysia","flag":"拆"},{"code":"MV","name":"Maldivez","flag":"拆"},{"code":"ML","name":"Mali","flag":"拆"},{"code":"MT","name":"Malta","flag":"拆"},{"code":"MR","name":"Maouritania","flag":"拆"},{"code":"MA","name":"Maroko","flag":"拆"},{"code":"MQ","name":"Martinik","flag":"拆"},{"code":"YT","name":"Mayotte","flag":"攫"},{"code":"MX","name":"Mec始hiko","flag":"拆"},{"code":"FM","name":"Mikronezia","flag":""},{"code":"MD","name":"Moldova","flag":"拆"},{"code":"MC","name":"Monaco","flag":"拆"},{"code":"MN","name":"Mongolia","flag":"拆"},{"code":"ME","name":"Montenegro","flag":"拆"},{"code":"MS","name":"Montserrat","flag":"拆"},{"code":"MU","name":"Moris","flag":"拆"},{"code":"MZ","name":"Mozambik","flag":"拆"},{"code":"MM","name":"Myanmar (Birmania)","flag":"拆"},{"code":"NA","name":"Namibia","flag":"仇"},{"code":"NR","name":"Nauru","flag":"仇"},{"code":"NP","name":"Nepal","flag":"仇"},{"code":"NI","name":"Nicaragua","flag":"仇"},{"code":"NE","name":"Niger","flag":"仇"},{"code":"NG","name":"Nigeria","flag":"仇"},{"code":"NU","name":"Niue","flag":"仇"},{"code":"NO","name":"Norvegia","flag":"仇"},{"code":"OM","name":"Oman","flag":"答"},{"code":"UG","name":"Ouganda","flag":"吼"},{"code":"UZ","name":"Ouzbekistan","flag":"吼"},{"code":"PK","name":"Pakistan","flag":"叼"},{"code":"PW","name":"Palau","flag":"叼"},{"code":"PA","name":"Panam谩","flag":"叼"},{"code":"PG","name":"Papoua Ginea-Nevez","flag":"叼"},{"code":"PY","name":"Paraguay","flag":"叼"},{"code":"PE","name":"Perou","flag":"叼"},{"code":"PF","name":"Polinezia C始hall","flag":"叼"},{"code":"PL","name":"Polonia","flag":"叼"},{"code":"PT","name":"Portugal","flag":"叼"},{"code":"PR","name":"Puerto Rico","flag":"叼"},{"code":"QA","name":"Qatar","flag":"娥"},{"code":"DO","name":"Republik Dominikan","flag":""},{"code":"CF","name":"Republik Kreizafrikan","flag":""},{"code":"CZ","name":"Republik Tchek","flag":""},{"code":"GB","name":"Rouantelezh-Unanet","flag":""},{"code":"RO","name":"Roumania","flag":"佛"},{"code":"RU","name":"Rusia","flag":"佛"},{"code":"RW","name":"Rwanda","flag":"佛"},{"code":"EH","name":"Sahara ar C始horn么g"},{"code":"BL","name":"Saint Barth茅lemy","flag":"ю"},{"code":"KN","name":"Saint Kitts ha Nevis","flag":"梆"},{"code":"LC","name":"Saint Lucia","flag":"别"},{"code":"MF","name":"Saint Martin","flag":"拆"},{"code":"SH","name":"Saint-Helena","flag":"葛"},{"code":"SV","name":"Salvador","flag":"葛"},{"code":"WS","name":"Samoa","flag":"拣"},{"code":"AS","name":"Samoa Amerikan","flag":""},{"code":"SM","name":"San Marino","flag":"葛"},{"code":"VC","name":"Sant Visant hag ar Grenadinez","flag":"火"},{"code":"PM","name":"Sant-P锚r-ha-Mikelon","flag":"叼"},{"code":"ST","name":"S茫o Tom茅 ha Pr铆ncipe","flag":"葛"},{"code":"SC","name":"Sechelez","flag":"葛"},{"code":"SN","name":"Senegal","flag":"葛"},{"code":"RS","name":"Serbia","flag":"佛"},{"code":"SL","name":"Sierra Leone","flag":"葛"},{"code":"CN","name":"Sina","flag":""},{"code":"SG","name":"Singapour","flag":"葛"},{"code":"SX","name":"Sint Maarten"},{"code":"SY","name":"Siria","flag":"葛"},{"code":"SK","name":"Slovakia","flag":"葛"},{"code":"SI","name":"Slovenia","flag":"葛"},{"code":"SO","name":"Somalia","flag":"葛"},{"code":"SD","name":"Soudan","flag":"葛"},{"code":"ES","name":"Spagn","flag":""},{"code":"LK","name":"Sri Lanka","flag":"别"},{"code":"US","name":"Stado霉-Unanet","flag":"吼"},{"code":"ZA","name":"Suafrika","flag":"筐"},{"code":"CH","name":"Suis","flag":""},{"code":"SR","name":"Surinam","flag":"葛"},{"code":"SS","name":"Susoudan","flag":"葛"},{"code":"SJ","name":"Svalbard","flag":"葛"},{"code":"SE","name":"Sveden","flag":"葛"},{"code":"SZ","name":"Swaziland","flag":"葛"},{"code":"TJ","name":"Tadjikistan","flag":"桂"},{"code":"TW","name":"Taiwan","flag":"桂"},{"code":"TZ","name":"Tanzania","flag":"桂"},{"code":"TD","name":"Tchad","flag":"桂"},{"code":"TH","name":"Thailand","flag":"桂"},{"code":"TL","name":"Timor-Leste","flag":"桂"},{"code":"IO","name":"Tiriad breizhveurat Meurvor Indez","flag":""},{"code":"PS","name":"Tiriado霉 Palestina","flag":"叼"},{"code":"TG","name":"Togo","flag":"桂"},{"code":"TK","name":"Tokelau","flag":"桂"},{"code":"TO","name":"Tonga","flag":"桂"},{"code":"TT","name":"Trinidad ha Tobago","flag":"桂"},{"code":"TA","name":"Tristan da Cunha"},{"code":"TN","name":"Tunizia","flag":"桂"},{"code":"TR","name":"Turkia","flag":"桂"},{"code":"TM","name":"Turkmenistan","flag":"桂"},{"code":"TV","name":"Tuvalu","flag":"桂"},{"code":"UA","name":"Ukraina","flag":"吼"},{"code":"UN","name":"United Nations"},{"code":"UY","name":"Uruguay","flag":"吼"},{"code":"VU","name":"Vanuatu","flag":"火"},{"code":"VA","name":"Vatikan","flag":"火"},{"code":"VE","name":"Venezuela","flag":"火"},{"code":"VN","name":"Vi锚t Nam","flag":"火"},{"code":"WF","name":"Wallis ha Futuna","flag":"拣"},{"code":"YE","name":"Yemen","flag":"攫"},{"code":"ZM","name":"Zambia","flag":"筐"},{"code":"NZ","name":"Zeland-Nevez","flag":"仇"},{"code":"ZW","name":"Zimbabwe","flag":"筐"}]