[{"name":"An Aet칩ip","value":"ET","flag":"游쀯릖"},{"name":"An Afganast치in","value":"AF","flag":"游뷣릖"},{"name":"An Afraic Theas","value":"ZA","flag":"游游"},{"name":"An Ailg칠ir","value":"DZ","flag":"游뾇릖"},{"name":"An Airgint칤n","value":"AR","flag":"游뷣릖"},{"name":"An Airm칠in","value":"AM","flag":"游뷣릖"},{"name":"An Alb치in","value":"AL","flag":"游뷣릖"},{"name":"An Antartaice","value":"AQ","flag":"游뷣릖"},{"name":"An Araib Sh치dach","value":"SA","flag":"游젏릖"},{"name":"An Asarbaise치in","value":"AZ","flag":"游뷣릖"},{"name":"An Astr치il","value":"AU","flag":"游뷣릖"},{"name":"An Bhanglaid칠is","value":"BD","flag":"游游"},{"name":"An Bhealar칰is","value":"BY","flag":"游游"},{"name":"An Bheilg","value":"BE","flag":"游游"},{"name":"An Bheil칤s","value":"BZ","flag":"游游"},{"name":"An Bhoisnia agus An Heirseagaiv칠in","value":"BA","flag":"游游"},{"name":"An Bholaiv","value":"BO","flag":"游游"},{"name":"An Bhotsu치in","value":"BW","flag":"游游"},{"name":"An Bhrasa칤l","value":"BR","flag":"游游"},{"name":"An Bhulg치ir","value":"BG","flag":"游游"},{"name":"An Bhur칰in","value":"BI","flag":"游游"},{"name":"An Bh칰t치in","value":"BT","flag":"游游"},{"name":"An Chamb칩id","value":"KH","flag":"游썷릖"},{"name":"An Chasacst치in","value":"KZ","flag":"游썷릖"},{"name":"An Ch칠inia","value":"KE","flag":"游썷릖"},{"name":"An Chipir","value":"CY","flag":"游뻟릖"},{"name":"An Chirgeast치in","value":"KG","flag":"游썷릖"},{"name":"An Ch칩ir칠 Theas","value":"KR","flag":"游썷릖"},{"name":"An Ch칩ir칠 Thuaidh","value":"KP","flag":"游썷릖"},{"name":"An Chol칩im","value":"CO","flag":"游뻟릖"},{"name":"An Chr칩it","value":"HR","flag":"游쇓릖"},{"name":"An Cong칩","value":"CG","flag":"游뻟릖"},{"name":"An C칩sta Eabhair","value":"CI","flag":"游뻟릖"},{"name":"An Danmhairg","value":"DK","flag":"游뾇릖"},{"name":"An East칩in","value":"EE","flag":"游쀯릖"},{"name":"An 칄igipt","value":"EG","flag":"游쀯릖"},{"name":"An Eilv칠is","value":"CH","flag":"游뻟릖"},{"name":"An Eiritr칠","value":"ER","flag":"游쀯릖"},{"name":"An Fhionlainn","value":"FI","flag":"游游"},{"name":"An Fhrainc","value":"FR","flag":"游游"},{"name":"An Ghab칰in","value":"GA","flag":"游섫릖"},{"name":"An Ghaimbia","value":"GM","flag":"游섫릖"},{"name":"An Ghearm치in","value":"DE","flag":"游뾇릖"},{"name":"An Ghraonlainn","value":"GL","flag":"游섫릖"},{"name":"An Ghr칠ig","value":"GR","flag":"游섫릖"},{"name":"An Ghu치in","value":"GY","flag":"游섫릖"},{"name":"An Ghuine","value":"GN","flag":"游섫릖"},{"name":"An Ghuine Mhe치nchriosach","value":"GQ","flag":"游섫릖"},{"name":"An Iar치ic","value":"IQ","flag":"游쉻릖"},{"name":"An Iar치in","value":"IR","flag":"游쉻릖"},{"name":"An India","value":"IN","flag":"游쉻릖"},{"name":"An Indin칠is","value":"ID","flag":"游쉻릖"},{"name":"An Iod치il","value":"IT","flag":"游쉻릖"},{"name":"An Iord치in","value":"JO","flag":"游游"},{"name":"An Iorua","value":"NO","flag":"游游"},{"name":"An 칈oslainn","value":"IS","flag":"游쉻릖"},{"name":"An 칈silt칤r","value":"NL","flag":"游游"},{"name":"An Laitvia","value":"LV","flag":"游쐟릖"},{"name":"An Lib칠ir","value":"LR","flag":"游쐟릖"},{"name":"An Libia","value":"LY","flag":"游쐟릖"},{"name":"An Liob치in","value":"LB","flag":"游쐟릖"},{"name":"An Liotu치in","value":"LT","flag":"游쐟릖"},{"name":"An Mhacad칩in","value":"MK","flag":"游쓇릖"},{"name":"An Mhalaeisia","value":"MY","flag":"游쓇릖"},{"name":"An Mhal치iv","value":"MW","flag":"游쓇릖"},{"name":"An Mh치rat치in","value":"MR","flag":"游쓇릖"},{"name":"An Mhicrin칠is","value":"FM","flag":"游游"},{"name":"An Mhold칩iv","value":"MD","flag":"游쓇릖"},{"name":"An Mhong칩il","value":"MN","flag":"游쓇릖"},{"name":"An Namaib","value":"NA","flag":"游游"},{"name":"An Nig칠ir","value":"NG","flag":"游游"},{"name":"An N칤gir","value":"NE","flag":"游游"},{"name":"An Nua-Chalad칩in","value":"NC","flag":"游游"},{"name":"An Nua-Sh칠alainn","value":"NZ","flag":"游游"},{"name":"An Ostair","value":"AT","flag":"游뷣릖"},{"name":"An Phacast치in","value":"PK","flag":"游왫릖"},{"name":"An Phoblacht Dhoiminiceach","value":"DO","flag":"游뾇릖"},{"name":"An Pholainn","value":"PL","flag":"游왫릖"},{"name":"An Phortaing칠il","value":"PT","flag":"游왫릖"},{"name":"An R칤ocht Aontaithe","value":"GB","flag":"游섫릖"},{"name":"An R칩m치in","value":"RO","flag":"游游"},{"name":"An R칰is","value":"RU","flag":"游游"},{"name":"An Sp치inn","value":"ES","flag":"游쀯릖"},{"name":"An T치ids칤ceast치in","value":"TJ","flag":"游좷릖"},{"name":"An Tans치in","value":"TZ","flag":"游좷릖"},{"name":"An T칠alainn","value":"TH","flag":"游좷릖"},{"name":"An T칠av치in","value":"TW","flag":"游좷릖"},{"name":"An tSaimbia","value":"ZM","flag":"游游"},{"name":"An tSalvad칩ir","value":"SV","flag":"游젏릖"},{"name":"An tSeap치in","value":"JP","flag":"游游"},{"name":"An tSeineag치il","value":"SN","flag":"游젏릖"},{"name":"An tSeirbia","value":"RS","flag":"游游"},{"name":"An tSeoirsia","value":"GE","flag":"游섫릖"},{"name":"An tSeoirsia Theas agus Oile치in Sandwich Theas","value":"GS","flag":"游섫릖"},{"name":"An tSile","value":"CL","flag":"游뻟릖"},{"name":"An tS칤n","value":"CN","flag":"游뻟릖"},{"name":"An tSiomb치ib","value":"ZW","flag":"游游"},{"name":"An tSiria","value":"SY","flag":"游젏릖"},{"name":"An tSl칩iv칠in","value":"SI","flag":"游젏릖"},{"name":"An tSl칩vaic","value":"SK","flag":"游젏릖"},{"name":"An tSom치il","value":"SO","flag":"游젏릖"},{"name":"An tSualainn","value":"SE","flag":"游젏릖"},{"name":"An tSuasalainn","value":"SZ","flag":"游젏릖"},{"name":"An tS칰d치in","value":"SD","flag":"游젏릖"},{"name":"An tS칰d치in Theas","value":"SS","flag":"游젏릖"},{"name":"An T칰in칠is","value":"TN","flag":"游좷릖"},{"name":"An Tuirc","value":"TR","flag":"游좷릖"},{"name":"An Tuircm칠anast치in","value":"TM","flag":"游좷릖"},{"name":"An 칔cr치in","value":"UA","flag":"游쥟릖"},{"name":"An 칔isb칠iceast치in","value":"UZ","flag":"游쥟릖"},{"name":"An Ung치ir","value":"HU","flag":"游쇓릖"},{"name":"An Vatac치in","value":"VA","flag":"游游"},{"name":"And칩ra","value":"AD","flag":"游뷣릖"},{"name":"Anga칤le","value":"AI","flag":"游뷣릖"},{"name":"Ang칩la","value":"AO","flag":"游뷣릖"},{"name":"Antigua agus Barb칰da","value":"AG","flag":"游뷣릖"},{"name":"Aontas na n칄im칤r칤ochta칤 Arabacha","value":"AE","flag":"游뷣릖"},{"name":"Ar칰ba","value":"AW","flag":"游뷣릖"},{"name":"Bair칠in","value":"BH","flag":"游游"},{"name":"Barbad칩s","value":"BB","flag":"游游"},{"name":"Beinin","value":"BJ","flag":"游游"},{"name":"Beirmi칰da","value":"BM","flag":"游游"},{"name":"Br칰in칠","value":"BN","flag":"游游"},{"name":"Buirc칤ne Fas칩","value":"BF","flag":"游游"},{"name":"Camar칰n","value":"CM","flag":"游뻟릖"},{"name":"Catar","value":"QA","flag":"游윓릖"},{"name":"Ceanada","value":"CA","flag":"游뻟릖"},{"name":"Cireabait칤","value":"KI","flag":"游썷릖"},{"name":"C칩sta R칤ce","value":"CR","flag":"游뻟릖"},{"name":"Cr칤och Aig칠an Indiach na Breataine","value":"IO","flag":"游쉻릖"},{"name":"Cu치it","value":"KW","flag":"游썷릖"},{"name":"C칰ba","value":"CU","flag":"游뻟릖"},{"name":"Djibouti","value":"DJ","flag":"游뾇릖"},{"name":"Doiminice","value":"DM","flag":"游뾇릖"},{"name":"Eacuad칩r","value":"EC","flag":"游쀯릖"},{"name":"칄imin","value":"YE","flag":"游쮫릖"},{"name":"칄ire","value":"IE","flag":"游쉻릖"},{"name":"Fids칤","value":"FJ","flag":"游游"},{"name":"G치na","value":"GH","flag":"游섫릖"},{"name":"Geansa칤","value":"GG","flag":"游섫릖"},{"name":"Geirs칤","value":"JE","flag":"游游"},{"name":"Giobr치ltar","value":"GI","flag":"游섫릖"},{"name":"Grean치da","value":"GD","flag":"游섫릖"},{"name":"Guadal칰ip","value":"GP","flag":"游섫릖"},{"name":"Gu치in na Fraince","value":"GF","flag":"游섫릖"},{"name":"Guam","value":"GU","flag":"游섫릖"},{"name":"Guatamala","value":"GT","flag":"游섫릖"},{"name":"Guine Bissau","value":"GW","flag":"游섫릖"},{"name":"H치칤t칤","value":"HT","flag":"游쇓릖"},{"name":"Hond칰ras","value":"HN","flag":"游쇓릖"},{"name":"Iam치ice","value":"JM","flag":"游游"},{"name":"Iosrael","value":"IL","flag":"游쉻릖"},{"name":"Laos","value":"LA","flag":"游쐟릖"},{"name":"Leos칩ta","value":"LS","flag":"游쐟릖"},{"name":"Lichtinst칠in","value":"LI","flag":"游쐟릖"},{"name":"Lucsamburg","value":"LU","flag":"游쐟릖"},{"name":"Madagascar","value":"MG","flag":"游쓇릖"},{"name":"Maenmar (Burma)","value":"MM","flag":"游쓇릖"},{"name":"Mail칤","value":"ML","flag":"游쓇릖"},{"name":"M치lta","value":"MT","flag":"游쓇릖"},{"name":"Marac칩","value":"MA","flag":"游쓇릖"},{"name":"Martinique","value":"MQ","flag":"游쓇릖"},{"name":"Mayotte","value":"YT","flag":"游쮫릖"},{"name":"Meicsiceo","value":"MX","flag":"游쓇릖"},{"name":"Monac칩","value":"MC","flag":"游쓇릖"},{"name":"Montain칠agr칩","value":"ME","flag":"游쓇릖"},{"name":"Montsarat","value":"MS","flag":"游쓇릖"},{"name":"M칩saimb칤c","value":"MZ","flag":"游쓇릖"},{"name":"Na Bah치ma칤","value":"BS","flag":"游游"},{"name":"Na Cr칤ocha Palaist칤neacha","value":"PS","flag":"游왫릖"},{"name":"Na hOile치in Fhilip칤neacha","value":"PH","flag":"游왫릖"},{"name":"Na hOile치in Mh치irianacha Thuaidh","value":"MP","flag":"游쓇릖"},{"name":"Na S칠is칠il","value":"SC","flag":"游젏릖"},{"name":"N치r칰","value":"NR","flag":"游游"},{"name":"Neipeal","value":"NP","flag":"游游"},{"name":"Nicearagua","value":"NI","flag":"游游"},{"name":"Niue","value":"NU","flag":"游游"},{"name":"Nua-Ghuine Phapua","value":"PG","flag":"游왫릖"},{"name":"Oile치in 칀land","value":"AX","flag":"游뷣릖"},{"name":"Oile치in Bhriotanacha na Maighdean","value":"VG","flag":"游游"},{"name":"Oile치in Cayman","value":"KY","flag":"游썷릖"},{"name":"Oile치in Chom칩ra","value":"KM","flag":"游썷릖"},{"name":"Oile치in Cocos (Keeling)","value":"CC","flag":"游뻟릖"},{"name":"Oile치in Cook","value":"CK","flag":"游뻟릖"},{"name":"Oile치in Fh치clainne","value":"FK","flag":"游游"},{"name":"Oile치in Fhar칩","value":"FO","flag":"游游"},{"name":"Oile치in Marshall","value":"MH","flag":"游쓇릖"},{"name":"Oile치in Mhaild칤ve","value":"MV","flag":"游쓇릖"},{"name":"Oile치in Mheirice치nacha na Maighdean","value":"VI","flag":"游游"},{"name":"Oile치in na dTurcach agus Caicos","value":"TC","flag":"游좷릖"},{"name":"Oile치in Pitcairn","value":"PN","flag":"游왫릖"},{"name":"Oile치in Sholom칩n","value":"SB","flag":"游젏릖"},{"name":"Oile치n Mhanann","value":"IM","flag":"游쉻릖"},{"name":"Oile치n Mhuir칤s","value":"MU","flag":"游쓇릖"},{"name":"Oile치n na Nollag","value":"CX","flag":"游뻟릖"},{"name":"Oile치n na Tr칤on칩ide agus Tob치ga","value":"TT","flag":"游좷릖"},{"name":"Oile치n Norfolk","value":"NF","flag":"游游"},{"name":"칍man","value":"OM","flag":"游엃릖"},{"name":"Palau","value":"PW","flag":"游왫릖"},{"name":"Panama","value":"PA","flag":"游왫릖"},{"name":"Paragua","value":"PY","flag":"游왫릖"},{"name":"Peiri칰","value":"PE","flag":"游왫릖"},{"name":"Poblacht Dhaonlathach an Chong칩","value":"CD","flag":"游뻟릖"},{"name":"Poblacht na hAfraice L치ir","value":"CF","flag":"游뻟릖"},{"name":"Poblacht na Seice","value":"CZ","flag":"游뻟릖"},{"name":"Polain칠is na Fraince","value":"PF","flag":"游왫릖"},{"name":"Port칩 R칤ce","value":"PR","flag":"游왫릖"},{"name":"R칠union","value":"RE","flag":"游游"},{"name":"Rinn Verde","value":"CV","flag":"游뻟릖"},{"name":"Ruanda","value":"RW","flag":"游游"},{"name":"S.R.R. na S칤ne Hong Cong","value":"HK","flag":"游쇓릖"},{"name":"S.R.R. na S칤ne Macao","value":"MO","flag":"游쓇릖"},{"name":"Saint Barth칠lemy","value":"BL","flag":"游游"},{"name":"Saint Lucia","value":"LC","flag":"游쐟릖"},{"name":"Saint-Martin","value":"MF","flag":"游쓇릖"},{"name":"Saint-Pierre-et-Miquelon","value":"PM","flag":"游왫릖"},{"name":"Sam칩","value":"WS","flag":"游쩛릖"},{"name":"Sam칩 Meirice치nach","value":"AS","flag":"游뷣릖"},{"name":"San Cr칤ost칩ir-Nimheas","value":"KN","flag":"游썷릖"},{"name":"San H칠ilin","value":"SH","flag":"游젏릖"},{"name":"San Mair칤ne","value":"SM","flag":"游젏릖"},{"name":"San Uinseann agus na Grean치id칤n칤","value":"VC","flag":"游游"},{"name":"S칚o Tom칠 agus Pr칤ncipe","value":"ST","flag":"游젏릖"},{"name":"Sead","value":"TD","flag":"游좷릖"},{"name":"Siarra Leon","value":"SL","flag":"游젏릖"},{"name":"Singeap칩r","value":"SG","flag":"游젏릖"},{"name":"Sr칤 Lanca","value":"LK","flag":"游쐟릖"},{"name":"St치it Aontaithe Mheirice치","value":"US","flag":"游쥟릖"},{"name":"Suranam","value":"SR","flag":"游젏릖"},{"name":"Svalbard agus Jan Mayen","value":"SJ","flag":"游젏릖"},{"name":"T칤om칩r Thoir","value":"TL","flag":"游좷릖"},{"name":"T칩cal치","value":"TK","flag":"游좷릖"},{"name":"T칩ga","value":"TG","flag":"游좷릖"},{"name":"Tonga","value":"TO","flag":"游좷릖"},{"name":"Tuvalu","value":"TV","flag":"游좷릖"},{"name":"Uganda","value":"UG","flag":"游쥟릖"},{"name":"Urugua","value":"UY","flag":"游쥟릖"},{"name":"Vail칤s agus Fut칰na","value":"WF","flag":"游쩛릖"},{"name":"Vanuat칰","value":"VU","flag":"游游"},{"name":"Veinis칠ala","value":"VE","flag":"游游"},{"name":"V칤tneam","value":"VN","flag":"游游"}]